{"first1":[{"type":"title","interview":true,"title":"一、指挥"},{"type":"select","label":"乐曲类型","labelWidth":"75px","value":"","range":[2,3,4],"options":[{"value":"管弦乐曲一首","show":[2]},{"value":"交响曲一个乐章","show":[2]},{"value":"合唱曲两首","show":[3,4]}]},{"type":"input","hide":true,"label":"曲目名称","labelWidth":"75px","value":"","author":""},{"type":"input","hide":true,"label":"合唱曲一","labelWidth":"75px","value":"","author":""},{"type":"input","hide":true,"label":"合唱曲二","labelWidth":"75px","value":"","author":""},{"type":"title","interview":true,"title":"二、综合基础面试"},{"type":"cascader","label":"主试乐器","value":[],"piano":[7,8,9,10],"others":[7,8,10]},{"type":"input","hide":true,"label":"练习曲","labelWidth":"60px","value":"","author":""},{"type":"input","hide":true,"label":"大型乐曲","labelWidth":"75px","value":"","author":""},{"type":"input","hide":true,"label":"三声部以上复调","labelWidth":"115px","value":"","author":""},{"type":"select","hide":true,"label":"报考方向","labelWidth":"75px","value":"","range":[11,12],"options":[{"value":"合唱指挥","show":[11,12]},{"value":"其它","show":[]}]},{"type":"input","hide":true,"label":"中文歌曲","labelWidth":"75px","value":"","author":""},{"type":"input","hide":true,"label":"外文歌曲","labelWidth":"75px","value":"","author":""}],"first2":[{"type":"text","text":"无"}],"second":[{"type":"title","interview":false,"title":"一、和声"},{"type":"title","interview":true,"title":"二、钢琴"},{"type":"select","label":"主试乐器","labelWidth":"75px","value":"","range":[3,4,5,6,7,8,9],"options":[{"value":"钢琴","show":[3,4,5,6]},{"value":"其它","show":[3,7,8,9]}]},{"type":"input","hide":true,"label":"练习曲","labelWidth":"60px","value":"","author":""},{"type":"input","hide":true,"label":"大型乐曲","labelWidth":"75px","value":"","author":""},{"type":"input","hide":true,"label":"三声部以上复调","labelWidth":"115px","value":"","author":""},{"type":"input","hide":true,"label":"小型乐曲","labelWidth":"75px","value":"","author":""},{"type":"input","hide":true,"label":"曲目名称","labelWidth":"75px","value":"","author":""},{"type":"input","hide":true,"label":"复调乐曲","labelWidth":"75px","value":"","author":""},{"type":"text","hide":true,"text":"视奏临时指定乐曲"}],"third":[{"type":"title","interview":false,"title":"一、笔试（听写）A"},{"type":"title","interview":true,"title":"二、视唱A"},{"type":"title","interview":false,"title":"三、乐理"}]}